hikson/__init__.py
hikson/hikaro_json.py
hikson/json_handler.py
HikSon-0.2.0.dist-info/METADATA
HikSon-0.2.0.dist-info/WHEEL
HikSon-0.2.0.dist-info/top_level.txt
HikSon-0.2.0.dist-info/RECORD
