Metadata-Version: 2.1
Name: HikSon
Version: 0.2.0
Summary: An easier method to read, edit, and save data in JSONs
Home-page: https://github.com/1cz1/HikSon
Author: Hikaro
Author-email: contact@hikarox64.com
Classifier: Programming Language :: Python :: 3
Classifier: License :: OSI Approved :: MIT License
Classifier: Operating System :: OS Independent
Requires-Python: >=3.6
